nvidia_smi_remote/__init__.py
nvidia_smi_remote/main.py
nvidia_smi_remote-0.1.2.dist-info/LICENSE
nvidia_smi_remote-0.1.2.dist-info/METADATA
nvidia_smi_remote-0.1.2.dist-info/WHEEL
nvidia_smi_remote-0.1.2.dist-info/entry_points.txt
nvidia_smi_remote-0.1.2.dist-info/top_level.txt
nvidia_smi_remote-0.1.2.dist-info/RECORD
