Metadata-Version: 2.1
Name: nvidia-smi-remote
Version: 0.1.2
Summary: CLI tool to query GPU status remotely (based on nvidia-smi)
Author: HEEWON KIM
Author-email: ive2go@naver.com
License: MIT
Requires-Python: >=3.8
License-File: LICENSE
Requires-Dist: paramiko
Requires-Dist: blessed
